{"hostname":"www.funk.co.nz","url":"https://www.funk.co.nz/menu/about.php","filename":"-menu-about.php","linksCount":37,"linksArray":["https://www.funk.co.nz/","https://www.funk.co.nz/menu/about-author.php","https://www.funk.co.nz/blog/","https://www.funk.co.nz/blog/category/rants","https://www.funk.co.nz/blog/category/politics","https://www.funk.co.nz/blog/category/technology","https://www.funk.co.nz/netstat","https://www.funk.co.nz/blog/politics/5-world-leaders-visit-afghanistan-december-2010","https://www.funk.co.nz/blog/category/technology/things-related-to-mac-os","https://www.funk.co.nz/blog/category/online-marketing","https://www.funk.co.nz/blog/category/online-marketing/google-analytics","https://www.funk.co.nz/blog/category/online-marketing/google-adwords","https://www.funk.co.nz/blog/category/seo","https://www.funk.co.nz/blog/category/music","https://www.funk.co.nz/blog/category/visuals","https://www.funk.co.nz/cv/","https://www.funk.co.nz/menu/contact.php","https://www.funk.co.nz/amu/","https://www.funk.co.nz/blog/business/the-tomachi-corporation-is-a-go","https://www.funk.co.nz/h/","https://www.funk.co.nz/menu/search.php","https://www.funk.co.nz/aminosee/","https://www.funk.co.nz/mr/","https://www.funk.co.nz/tiri/","https://www.funk.co.nz/blog/visuals/my-recent-laser-cut-fractal-artworks","https://www.funk.co.nz/blog/product/box-of-doom-lichtenberg-etching-machine","https://www.funk.co.nz/tomachi/","https://www.funk.co.nz/auckland-music-update/","https://www.funk.co.nz/auckland-music-update/music-video-sex-girls-caught-tourettes-triptonites/","https://www.funk.co.nz/damnative/","https://www.funk.co.nz/sjd/","https://www.funk.co.nz/blog/music/breaks-co-op-uk-tour-2006-tour-dates","https://www.funk.co.nz/foghorn/","https://www.funk.co.nz/omd/","https://www.funk.co.nz/auckland-music-update/hmx-flyer/","https://www.funk.co.nz/roughness/","https://www.funk.co.nz/jf/"],"title":"404 File Not Found in the Funk: (101.98.182.135)www.funk.co.nz%2Fmenu%2Fabout.php","images":["https://www.funk.co.nz/images/nav/funk-logo-140px.png","https://www.funk.co.nz/images/nav/run-room.gif","https://www.funk.co.nz/images/pre2000/sig.gif"],"description":"About\nGraphics\nTomachi\nSearch\n404 - File Not Found\nWelcome to funk.co.nz, unfortunately the file you requested is not present on this server. Check your spelling, make sure there are no spaces or capital letters in the URL, and then try again. Alternatively, you can go to the Homepage.\n        Your IP address: 101.98.182.135 \n Keywords:  menu about.php      "}